{
  "display_manager_config": {
    "width": 1280,
    "height": 800,
    "title": "SteamRot",
    "framerate_limit": 60,
    "background_color": {
      "r": 49,
      "g": 50,
      "b": 68,
      "a": 255
    }
  },
  "tile_config": {
    "active_border_colour": {
      "r": 166,
      "g": 227,
      "b": 161
    },
    "inactive_border_colour": {
      "r": 205,
      "g": 214,
      "b": 244
    },
    "margin": {
      "x": 2.5,
      "y": 2.5
    },
    "border_thickness": {
      "x": 5,
      "y": 5
    },
    "radius_resolution": 15
  }
}
